importkit/__init__.py
importkit/context.py
importkit/exceptions.py
importkit/languages.py
importkit/loader.py
importkit/meta.py
importkit/runtimes.py
importkit/tests.py
importkit/__pycache__/__init__.cpython-36.pyc
importkit/__pycache__/context.cpython-36.pyc
importkit/__pycache__/exceptions.cpython-36.pyc
importkit/__pycache__/loader.cpython-36.pyc
importkit/__pycache__/meta.cpython-36.pyc
importkit/__pycache__/runtimes.cpython-36.pyc
importkit/import_/__init__.py
importkit/import_/_spec.py
importkit/import_/cache.py
importkit/import_/context.py
importkit/import_/finder.py
importkit/import_/loader.py
importkit/import_/module.py
importkit/import_/spec.py
importkit/import_/utils.py
importkit/import_/__pycache__/__init__.cpython-36.pyc
importkit/import_/__pycache__/cache.cpython-36.pyc
importkit/import_/__pycache__/context.cpython-36.pyc
importkit/import_/__pycache__/finder.cpython-36.pyc
importkit/import_/tests/__init__.py
importkit/import_/tests/test_proxy.py
importkit/import_/tests/__pycache__/__init__.cpython-36.pyc
importkit/import_/tests/__pycache__/test_proxy.cpython-36.pyc
importkit/import_/tests/testdata/__init__.py
importkit/import_/tests/testdata/proxiedmod.py
importkit/import_/tests/testdata/__pycache__/__init__.cpython-36.pyc
importkit/import_/tests/testdata/__pycache__/proxiedmod.cpython-36.pyc
importkit/python/__init__.py
importkit/python/utils.py
importkit/python/__pycache__/__init__.cpython-36.pyc
importkit/python/__pycache__/utils.cpython-36.pyc
importkit/python/tests/__init__.py
importkit/python/tests/test_utils.py
importkit/python/tests/__pycache__/__init__.cpython-36.pyc
importkit/python/tests/__pycache__/test_utils.cpython-36.pyc
importkit/utils/__init__.py
importkit/utils/adapter.py
importkit/utils/debug.py
importkit/utils/ordered.py
importkit/utils/registry.py
importkit/utils/topological.py
importkit/yaml/__init__.py
importkit/yaml/constructor.py
importkit/yaml/dumper.py
importkit/yaml/exceptions.py
importkit/yaml/loader.py
importkit-0.5.8.dist-info/LICENSE
importkit-0.5.8.dist-info/METADATA
importkit-0.5.8.dist-info/WHEEL
importkit-0.5.8.dist-info/pbr.json
importkit-0.5.8.dist-info/top_level.txt
importkit-0.5.8.dist-info/RECORD
