Metadata-Version: 2.1
Name: importkit
Version: 0.5.8
Summary: Importkit is a Python library for making anything importable as a Python module.
Home-page: https://github.com/sprymix/importkit
Maintainer: Sprymix Inc.
Maintainer-email: into@sprymix.com
License: UNKNOWN
Platform: any
Classifier: Development Status :: 4 - Beta
Classifier: Intended Audience :: Developers
Classifier: License :: OSI Approved :: MIT License
Classifier: Operating System :: OS Independent
Classifier: Programming Language :: Python :: 3
Classifier: Programming Language :: Python :: 3.4
Classifier: Programming Language :: Python :: 3.5
Requires-Dist: PyYAML (>=3.11)
